devcache/__init__.py
devcache/cache.py
devcache/storage.py
devcache/utils.py
devcache-1.0.2.dist-info/METADATA
devcache-1.0.2.dist-info/WHEEL
devcache-1.0.2.dist-info/top_level.txt
devcache-1.0.2.dist-info/RECORD
