Metadata-Version: 2.1
Name: devcache
Version: 1.0.2
Summary: Provides caching decorator to help speedup development
Home-page: https://github.com/pcauthorn/devcache
Author: Patrick Cauthorn
Author-email: patrick.cauthorn@gmail.com
License: MIT
Platform: UNKNOWN
Classifier: Topic :: Utilities
Classifier: License :: OSI Approved :: MIT License
Requires-Dist: pyYAML
Requires-Dist: setuptools
